libManager/__init__.py
libManager/main.py
libManager-0.1.2.dist-info/METADATA
libManager-0.1.2.dist-info/WHEEL
libManager-0.1.2.dist-info/top_level.txt
libManager-0.1.2.dist-info/RECORD
