Metadata-Version: 2.1
Name: libManager
Version: 0.1.2
Summary: A class providing more control over libraries using pip
Author: Kirill Sedykh
Author-email: kirill-10c@mail.ru
License: MIT
